[{"subreddit": "asheville", "hour": "01", "avg": 5.2272727272727275}, {"subreddit": "asheville", "hour": "02", "avg": 11.266666666666667}, {"subreddit": "asheville", "hour": "03", "avg": 7.588235294117647}, {"subreddit": "asheville", "hour": "04", "avg": 7.636363636363637}, {"subreddit": "asheville", "hour": "05", "avg": 7.769230769230769}, {"subreddit": "asheville", "hour": "06", "avg": 4.571428571428571}, {"subreddit": "asheville", "hour": "07", "avg": 28.25}, {"subreddit": "asheville", "hour": "08", "avg": 3.3333333333333335}, {"subreddit": "asheville", "hour": "09", "avg": 4.0}, {"subreddit": "asheville", "hour": "10", "avg": 7.5}, {"subreddit": "asheville", "hour": "11", "avg": 34.2}, {"subreddit": "asheville", "hour": "12", "avg": 7.8}, {"subreddit": "asheville", "hour": "13", "avg": 24.0}, {"subreddit": "asheville", "hour": "14", "avg": 8.48}, {"subreddit": "asheville", "hour": "15", "avg": 14.258064516129032}, {"subreddit": "asheville", "hour": "16", "avg": 6.096774193548387}, {"subreddit": "asheville", "hour": "17", "avg": 11.310344827586206}, {"subreddit": "asheville", "hour": "18", "avg": 21.0}, {"subreddit": "asheville", "hour": "19", "avg": 9.461538461538462}, {"subreddit": "asheville", "hour": "20", "avg": 14.083333333333334}, {"subreddit": "asheville", "hour": "21", "avg": 29.6}, {"subreddit": "asheville", "hour": "22", "avg": 14.724137931034482}, {"subreddit": "asheville", "hour": "23", "avg": 9.666666666666666}]