[{"subreddit": "AskEurope", "hour": "01", "avg": 9.08}, {"subreddit": "AskEurope", "hour": "02", "avg": 9.891891891891891}, {"subreddit": "AskEurope", "hour": "03", "avg": 19.533333333333335}, {"subreddit": "AskEurope", "hour": "04", "avg": 8.758620689655173}, {"subreddit": "AskEurope", "hour": "05", "avg": 18.17391304347826}, {"subreddit": "AskEurope", "hour": "06", "avg": 23.647058823529413}, {"subreddit": "AskEurope", "hour": "07", "avg": 21.789473684210527}, {"subreddit": "AskEurope", "hour": "08", "avg": 32.97142857142857}, {"subreddit": "AskEurope", "hour": "09", "avg": 9.659090909090908}, {"subreddit": "AskEurope", "hour": "10", "avg": 34.55102040816327}, {"subreddit": "AskEurope", "hour": "11", "avg": 25.916666666666668}, {"subreddit": "AskEurope", "hour": "12", "avg": 31.56140350877193}, {"subreddit": "AskEurope", "hour": "13", "avg": 10.1}, {"subreddit": "AskEurope", "hour": "14", "avg": 13.6}, {"subreddit": "AskEurope", "hour": "15", "avg": 15.346666666666666}, {"subreddit": "AskEurope", "hour": "16", "avg": 17.011764705882353}, {"subreddit": "AskEurope", "hour": "17", "avg": 15.19767441860465}, {"subreddit": "AskEurope", "hour": "18", "avg": 13.904761904761905}, {"subreddit": "AskEurope", "hour": "19", "avg": 8.653846153846153}, {"subreddit": "AskEurope", "hour": "20", "avg": 19.69047619047619}, {"subreddit": "AskEurope", "hour": "21", "avg": 11.125}, {"subreddit": "AskEurope", "hour": "22", "avg": 19.304878048780488}, {"subreddit": "AskEurope", "hour": "23", "avg": 16.56923076923077}]