[{"subreddit": "BigBlackBootyGIFS", "hour": "01", "avg": 138.27272727272728}, {"subreddit": "BigBlackBootyGIFS", "hour": "02", "avg": 118.625}, {"subreddit": "BigBlackBootyGIFS", "hour": "03", "avg": 182.46666666666667}, {"subreddit": "BigBlackBootyGIFS", "hour": "04", "avg": 143.64285714285714}, {"subreddit": "BigBlackBootyGIFS", "hour": "05", "avg": 102.875}, {"subreddit": "BigBlackBootyGIFS", "hour": "06", "avg": 117.83333333333333}, {"subreddit": "BigBlackBootyGIFS", "hour": "07", "avg": 103.25}, {"subreddit": "BigBlackBootyGIFS", "hour": "08", "avg": 120.0}, {"subreddit": "BigBlackBootyGIFS", "hour": "09", "avg": 110.0}, {"subreddit": "BigBlackBootyGIFS", "hour": "10", "avg": 37.0}, {"subreddit": "BigBlackBootyGIFS", "hour": "11", "avg": 61.75}, {"subreddit": "BigBlackBootyGIFS", "hour": "12", "avg": 136.85}, {"subreddit": "BigBlackBootyGIFS", "hour": "13", "avg": 96.9090909090909}, {"subreddit": "BigBlackBootyGIFS", "hour": "14", "avg": 106.11764705882354}, {"subreddit": "BigBlackBootyGIFS", "hour": "15", "avg": 162.66666666666666}, {"subreddit": "BigBlackBootyGIFS", "hour": "16", "avg": 55.166666666666664}, {"subreddit": "BigBlackBootyGIFS", "hour": "17", "avg": 99.0}, {"subreddit": "BigBlackBootyGIFS", "hour": "18", "avg": 130.16666666666666}, {"subreddit": "BigBlackBootyGIFS", "hour": "19", "avg": 92.25}, {"subreddit": "BigBlackBootyGIFS", "hour": "20", "avg": 87.0}, {"subreddit": "BigBlackBootyGIFS", "hour": "21", "avg": 52.111111111111114}, {"subreddit": "BigBlackBootyGIFS", "hour": "22", "avg": 121.83333333333333}, {"subreddit": "BigBlackBootyGIFS", "hour": "23", "avg": 34.833333333333336}]