[{"subreddit": "BitMarket", "hour": "01", "avg": 0.5714285714285714}, {"subreddit": "BitMarket", "hour": "02", "avg": 0.8571428571428571}, {"subreddit": "BitMarket", "hour": "03", "avg": 1.0}, {"subreddit": "BitMarket", "hour": "04", "avg": 1.3333333333333333}, {"subreddit": "BitMarket", "hour": "05", "avg": 0.875}, {"subreddit": "BitMarket", "hour": "06", "avg": 0.9}, {"subreddit": "BitMarket", "hour": "07", "avg": 1.0}, {"subreddit": "BitMarket", "hour": "08", "avg": 0.75}, {"subreddit": "BitMarket", "hour": "09", "avg": 1.5}, {"subreddit": "BitMarket", "hour": "10", "avg": 6.8}, {"subreddit": "BitMarket", "hour": "11", "avg": 1.0}, {"subreddit": "BitMarket", "hour": "12", "avg": 1.0}, {"subreddit": "BitMarket", "hour": "13", "avg": 1.0}, {"subreddit": "BitMarket", "hour": "14", "avg": 1.0}, {"subreddit": "BitMarket", "hour": "15", "avg": 0.9}, {"subreddit": "BitMarket", "hour": "16", "avg": 0.8571428571428571}, {"subreddit": "BitMarket", "hour": "17", "avg": 1.0}, {"subreddit": "BitMarket", "hour": "18", "avg": 1.6}, {"subreddit": "BitMarket", "hour": "19", "avg": 0.9285714285714286}, {"subreddit": "BitMarket", "hour": "20", "avg": 1.0}, {"subreddit": "BitMarket", "hour": "21", "avg": 0.625}, {"subreddit": "BitMarket", "hour": "22", "avg": 1.0}, {"subreddit": "BitMarket", "hour": "23", "avg": 1.2}]