[{"subreddit": "brexit", "hour": "01", "avg": 10.767441860465116}, {"subreddit": "brexit", "hour": "02", "avg": 22.636363636363637}, {"subreddit": "brexit", "hour": "03", "avg": 21.90909090909091}, {"subreddit": "brexit", "hour": "04", "avg": 27.941176470588236}, {"subreddit": "brexit", "hour": "05", "avg": 3.111111111111111}, {"subreddit": "brexit", "hour": "06", "avg": 14.0}, {"subreddit": "brexit", "hour": "07", "avg": 27.625}, {"subreddit": "brexit", "hour": "08", "avg": 31.867469879518072}, {"subreddit": "brexit", "hour": "09", "avg": 28.875}, {"subreddit": "brexit", "hour": "10", "avg": 22.71153846153846}, {"subreddit": "brexit", "hour": "11", "avg": 18.177966101694917}, {"subreddit": "brexit", "hour": "12", "avg": 17.194915254237287}, {"subreddit": "brexit", "hour": "13", "avg": 20.138297872340427}, {"subreddit": "brexit", "hour": "14", "avg": 21.451327433628318}, {"subreddit": "brexit", "hour": "15", "avg": 18.214285714285715}, {"subreddit": "brexit", "hour": "16", "avg": 14.2}, {"subreddit": "brexit", "hour": "17", "avg": 15.964285714285714}, {"subreddit": "brexit", "hour": "18", "avg": 21.225225225225227}, {"subreddit": "brexit", "hour": "19", "avg": 16.775862068965516}, {"subreddit": "brexit", "hour": "20", "avg": 20.504347826086956}, {"subreddit": "brexit", "hour": "21", "avg": 9.770491803278688}, {"subreddit": "brexit", "hour": "22", "avg": 13.708333333333334}, {"subreddit": "brexit", "hour": "23", "avg": 9.56338028169014}]