[{"subreddit": "CaptainTsubasaDT", "hour": "01", "avg": 6.066666666666666}, {"subreddit": "CaptainTsubasaDT", "hour": "02", "avg": 9.307692307692308}, {"subreddit": "CaptainTsubasaDT", "hour": "03", "avg": 10.083333333333334}, {"subreddit": "CaptainTsubasaDT", "hour": "04", "avg": 4.75}, {"subreddit": "CaptainTsubasaDT", "hour": "05", "avg": 4.541666666666667}, {"subreddit": "CaptainTsubasaDT", "hour": "06", "avg": 5.9523809523809526}, {"subreddit": "CaptainTsubasaDT", "hour": "07", "avg": 6.703703703703703}, {"subreddit": "CaptainTsubasaDT", "hour": "08", "avg": 7.583333333333333}, {"subreddit": "CaptainTsubasaDT", "hour": "09", "avg": 1.2}, {"subreddit": "CaptainTsubasaDT", "hour": "10", "avg": 0.8333333333333334}, {"subreddit": "CaptainTsubasaDT", "hour": "11", "avg": 5.842105263157895}, {"subreddit": "CaptainTsubasaDT", "hour": "12", "avg": 4.4375}, {"subreddit": "CaptainTsubasaDT", "hour": "13", "avg": 14.923076923076923}, {"subreddit": "CaptainTsubasaDT", "hour": "14", "avg": 3.9}, {"subreddit": "CaptainTsubasaDT", "hour": "15", "avg": 4.739130434782608}, {"subreddit": "CaptainTsubasaDT", "hour": "16", "avg": 5.190476190476191}, {"subreddit": "CaptainTsubasaDT", "hour": "17", "avg": 3.7777777777777777}, {"subreddit": "CaptainTsubasaDT", "hour": "18", "avg": 12.75}, {"subreddit": "CaptainTsubasaDT", "hour": "19", "avg": 5.222222222222222}, {"subreddit": "CaptainTsubasaDT", "hour": "20", "avg": 5.071428571428571}, {"subreddit": "CaptainTsubasaDT", "hour": "21", "avg": 5.933333333333334}, {"subreddit": "CaptainTsubasaDT", "hour": "22", "avg": 2.4166666666666665}, {"subreddit": "CaptainTsubasaDT", "hour": "23", "avg": 5.142857142857143}]