[{"subreddit": "chinesefood", "hour": "01", "avg": 31.6}, {"subreddit": "chinesefood", "hour": "02", "avg": 22.88888888888889}, {"subreddit": "chinesefood", "hour": "03", "avg": 7.5}, {"subreddit": "chinesefood", "hour": "04", "avg": 14.625}, {"subreddit": "chinesefood", "hour": "05", "avg": 50.875}, {"subreddit": "chinesefood", "hour": "06", "avg": 25.0}, {"subreddit": "chinesefood", "hour": "07", "avg": 7.166666666666667}, {"subreddit": "chinesefood", "hour": "08", "avg": 13.0}, {"subreddit": "chinesefood", "hour": "09", "avg": 2.0}, {"subreddit": "chinesefood", "hour": "10", "avg": 3.2}, {"subreddit": "chinesefood", "hour": "11", "avg": 12.75}, {"subreddit": "chinesefood", "hour": "12", "avg": 23.833333333333332}, {"subreddit": "chinesefood", "hour": "13", "avg": 22.0}, {"subreddit": "chinesefood", "hour": "14", "avg": 5.375}, {"subreddit": "chinesefood", "hour": "15", "avg": 26.2}, {"subreddit": "chinesefood", "hour": "16", "avg": 10.2}, {"subreddit": "chinesefood", "hour": "17", "avg": 20.8}, {"subreddit": "chinesefood", "hour": "18", "avg": 34.75}, {"subreddit": "chinesefood", "hour": "19", "avg": 22.333333333333332}, {"subreddit": "chinesefood", "hour": "20", "avg": 7.333333333333333}, {"subreddit": "chinesefood", "hour": "21", "avg": 9.75}, {"subreddit": "chinesefood", "hour": "22", "avg": 19.4}, {"subreddit": "chinesefood", "hour": "23", "avg": 13.833333333333334}]