[{"subreddit": "Dodge", "hour": "01", "avg": 49.3}, {"subreddit": "Dodge", "hour": "02", "avg": 37.8}, {"subreddit": "Dodge", "hour": "03", "avg": 27.357142857142858}, {"subreddit": "Dodge", "hour": "04", "avg": 18.0}, {"subreddit": "Dodge", "hour": "05", "avg": 7.666666666666667}, {"subreddit": "Dodge", "hour": "06", "avg": 6.25}, {"subreddit": "Dodge", "hour": "07", "avg": 6.333333333333333}, {"subreddit": "Dodge", "hour": "08", "avg": 7.0}, {"subreddit": "Dodge", "hour": "09", "avg": 10.25}, {"subreddit": "Dodge", "hour": "10", "avg": 0.75}, {"subreddit": "Dodge", "hour": "11", "avg": 1.0}, {"subreddit": "Dodge", "hour": "12", "avg": 23.0}, {"subreddit": "Dodge", "hour": "13", "avg": 34.6}, {"subreddit": "Dodge", "hour": "14", "avg": 23.333333333333332}, {"subreddit": "Dodge", "hour": "15", "avg": 32.214285714285715}, {"subreddit": "Dodge", "hour": "16", "avg": 27.857142857142858}, {"subreddit": "Dodge", "hour": "17", "avg": 39.0}, {"subreddit": "Dodge", "hour": "18", "avg": 3.8333333333333335}, {"subreddit": "Dodge", "hour": "19", "avg": 7.0}, {"subreddit": "Dodge", "hour": "20", "avg": 60.875}, {"subreddit": "Dodge", "hour": "21", "avg": 24.454545454545453}, {"subreddit": "Dodge", "hour": "22", "avg": 36.0}, {"subreddit": "Dodge", "hour": "23", "avg": 30.25}]