[{"subreddit": "dragonquest", "hour": "01", "avg": 36.69565217391305}, {"subreddit": "dragonquest", "hour": "02", "avg": 31.5}, {"subreddit": "dragonquest", "hour": "03", "avg": 33.476190476190474}, {"subreddit": "dragonquest", "hour": "04", "avg": 16.833333333333332}, {"subreddit": "dragonquest", "hour": "05", "avg": 18.5}, {"subreddit": "dragonquest", "hour": "06", "avg": 6.416666666666667}, {"subreddit": "dragonquest", "hour": "07", "avg": 34.733333333333334}, {"subreddit": "dragonquest", "hour": "08", "avg": 18.05263157894737}, {"subreddit": "dragonquest", "hour": "09", "avg": 30.142857142857142}, {"subreddit": "dragonquest", "hour": "10", "avg": 26.727272727272727}, {"subreddit": "dragonquest", "hour": "11", "avg": 5.25}, {"subreddit": "dragonquest", "hour": "12", "avg": 20.25}, {"subreddit": "dragonquest", "hour": "13", "avg": 40.4375}, {"subreddit": "dragonquest", "hour": "14", "avg": 28.11111111111111}, {"subreddit": "dragonquest", "hour": "15", "avg": 15.88888888888889}, {"subreddit": "dragonquest", "hour": "16", "avg": 17.285714285714285}, {"subreddit": "dragonquest", "hour": "17", "avg": 31.366666666666667}, {"subreddit": "dragonquest", "hour": "18", "avg": 10.782608695652174}, {"subreddit": "dragonquest", "hour": "19", "avg": 11.56}, {"subreddit": "dragonquest", "hour": "20", "avg": 32.9375}, {"subreddit": "dragonquest", "hour": "21", "avg": 19.0625}, {"subreddit": "dragonquest", "hour": "22", "avg": 15.333333333333334}, {"subreddit": "dragonquest", "hour": "23", "avg": 6.857142857142857}]