[{"subreddit": "dragonballfighterz", "hour": "01", "avg": 47.01169590643275}, {"subreddit": "dragonballfighterz", "hour": "02", "avg": 60.241379310344826}, {"subreddit": "dragonballfighterz", "hour": "03", "avg": 32.97402597402598}, {"subreddit": "dragonballfighterz", "hour": "04", "avg": 28.03053435114504}, {"subreddit": "dragonballfighterz", "hour": "05", "avg": 22.223214285714285}, {"subreddit": "dragonballfighterz", "hour": "06", "avg": 13.636363636363637}, {"subreddit": "dragonballfighterz", "hour": "07", "avg": 19.34375}, {"subreddit": "dragonballfighterz", "hour": "08", "avg": 63.59154929577465}, {"subreddit": "dragonballfighterz", "hour": "09", "avg": 28.1875}, {"subreddit": "dragonballfighterz", "hour": "10", "avg": 47.506493506493506}, {"subreddit": "dragonballfighterz", "hour": "11", "avg": 36.14666666666667}, {"subreddit": "dragonballfighterz", "hour": "12", "avg": 91.72463768115942}, {"subreddit": "dragonballfighterz", "hour": "13", "avg": 77.21}, {"subreddit": "dragonballfighterz", "hour": "14", "avg": 72.0}, {"subreddit": "dragonballfighterz", "hour": "15", "avg": 40.7593984962406}, {"subreddit": "dragonballfighterz", "hour": "16", "avg": 59.10655737704918}, {"subreddit": "dragonballfighterz", "hour": "17", "avg": 36.23717948717949}, {"subreddit": "dragonballfighterz", "hour": "18", "avg": 64.76258992805755}, {"subreddit": "dragonballfighterz", "hour": "19", "avg": 46.7}, {"subreddit": "dragonballfighterz", "hour": "20", "avg": 35.24285714285714}, {"subreddit": "dragonballfighterz", "hour": "21", "avg": 25.455696202531644}, {"subreddit": "dragonballfighterz", "hour": "22", "avg": 57.54022988505747}, {"subreddit": "dragonballfighterz", "hour": "23", "avg": 74.80104712041884}]