[{"subreddit": "Empaths", "hour": "01", "avg": 37.0}, {"subreddit": "Empaths", "hour": "02", "avg": 13.533333333333333}, {"subreddit": "Empaths", "hour": "03", "avg": 10.5}, {"subreddit": "Empaths", "hour": "04", "avg": 2.4444444444444446}, {"subreddit": "Empaths", "hour": "05", "avg": 6.818181818181818}, {"subreddit": "Empaths", "hour": "06", "avg": 18.833333333333332}, {"subreddit": "Empaths", "hour": "07", "avg": 22.125}, {"subreddit": "Empaths", "hour": "08", "avg": 6.333333333333333}, {"subreddit": "Empaths", "hour": "09", "avg": 1.0}, {"subreddit": "Empaths", "hour": "10", "avg": 3.0}, {"subreddit": "Empaths", "hour": "11", "avg": 5.0}, {"subreddit": "Empaths", "hour": "12", "avg": 2.0}, {"subreddit": "Empaths", "hour": "13", "avg": 20.166666666666668}, {"subreddit": "Empaths", "hour": "14", "avg": 22.666666666666668}, {"subreddit": "Empaths", "hour": "15", "avg": 17.272727272727273}, {"subreddit": "Empaths", "hour": "16", "avg": 8.3}, {"subreddit": "Empaths", "hour": "17", "avg": 19.846153846153847}, {"subreddit": "Empaths", "hour": "18", "avg": 9.428571428571429}, {"subreddit": "Empaths", "hour": "19", "avg": 9.947368421052632}, {"subreddit": "Empaths", "hour": "20", "avg": 12.619047619047619}, {"subreddit": "Empaths", "hour": "21", "avg": 2.9}, {"subreddit": "Empaths", "hour": "22", "avg": 16.875}, {"subreddit": "Empaths", "hour": "23", "avg": 6.833333333333333}]