[{"subreddit": "gaystoriesgonewild", "hour": "01", "avg": 99.25}, {"subreddit": "gaystoriesgonewild", "hour": "02", "avg": 67.06666666666666}, {"subreddit": "gaystoriesgonewild", "hour": "03", "avg": 89.15789473684211}, {"subreddit": "gaystoriesgonewild", "hour": "04", "avg": 88.52941176470588}, {"subreddit": "gaystoriesgonewild", "hour": "05", "avg": 52.4}, {"subreddit": "gaystoriesgonewild", "hour": "06", "avg": 35.142857142857146}, {"subreddit": "gaystoriesgonewild", "hour": "07", "avg": 27.85}, {"subreddit": "gaystoriesgonewild", "hour": "08", "avg": 15.210526315789474}, {"subreddit": "gaystoriesgonewild", "hour": "09", "avg": 11.545454545454545}, {"subreddit": "gaystoriesgonewild", "hour": "10", "avg": 32.76470588235294}, {"subreddit": "gaystoriesgonewild", "hour": "11", "avg": 58.875}, {"subreddit": "gaystoriesgonewild", "hour": "12", "avg": 166.0}, {"subreddit": "gaystoriesgonewild", "hour": "13", "avg": 72.5}, {"subreddit": "gaystoriesgonewild", "hour": "14", "avg": 44.0}, {"subreddit": "gaystoriesgonewild", "hour": "15", "avg": 38.36666666666667}, {"subreddit": "gaystoriesgonewild", "hour": "16", "avg": 84.13636363636364}, {"subreddit": "gaystoriesgonewild", "hour": "17", "avg": 21.454545454545453}, {"subreddit": "gaystoriesgonewild", "hour": "18", "avg": 76.25}, {"subreddit": "gaystoriesgonewild", "hour": "19", "avg": 76.79166666666667}, {"subreddit": "gaystoriesgonewild", "hour": "20", "avg": 83.9047619047619}, {"subreddit": "gaystoriesgonewild", "hour": "21", "avg": 112.77777777777777}, {"subreddit": "gaystoriesgonewild", "hour": "22", "avg": 75.10526315789474}, {"subreddit": "gaystoriesgonewild", "hour": "23", "avg": 63.31818181818182}]