[{"subreddit": "gigabyte", "hour": "01", "avg": 1.5}, {"subreddit": "gigabyte", "hour": "02", "avg": 1.375}, {"subreddit": "gigabyte", "hour": "03", "avg": 1.7142857142857142}, {"subreddit": "gigabyte", "hour": "04", "avg": 1.4}, {"subreddit": "gigabyte", "hour": "05", "avg": 2.0}, {"subreddit": "gigabyte", "hour": "06", "avg": 0.8333333333333334}, {"subreddit": "gigabyte", "hour": "07", "avg": 1.5}, {"subreddit": "gigabyte", "hour": "08", "avg": 2.2}, {"subreddit": "gigabyte", "hour": "09", "avg": 2.3333333333333335}, {"subreddit": "gigabyte", "hour": "10", "avg": 1.3333333333333333}, {"subreddit": "gigabyte", "hour": "11", "avg": 2.25}, {"subreddit": "gigabyte", "hour": "12", "avg": 1.6666666666666667}, {"subreddit": "gigabyte", "hour": "13", "avg": 2.8}, {"subreddit": "gigabyte", "hour": "14", "avg": 2.25}, {"subreddit": "gigabyte", "hour": "15", "avg": 1.5}, {"subreddit": "gigabyte", "hour": "16", "avg": 2.0}, {"subreddit": "gigabyte", "hour": "17", "avg": 2.0}, {"subreddit": "gigabyte", "hour": "18", "avg": 1.0}, {"subreddit": "gigabyte", "hour": "19", "avg": 1.5625}, {"subreddit": "gigabyte", "hour": "20", "avg": 1.3333333333333333}, {"subreddit": "gigabyte", "hour": "21", "avg": 6.75}, {"subreddit": "gigabyte", "hour": "22", "avg": 1.0}, {"subreddit": "gigabyte", "hour": "23", "avg": 1.2}]