[{"subreddit": "GoCommitDie", "hour": "01", "avg": 138.58549222797927}, {"subreddit": "GoCommitDie", "hour": "02", "avg": 126.36842105263158}, {"subreddit": "GoCommitDie", "hour": "03", "avg": 56.727777777777774}, {"subreddit": "GoCommitDie", "hour": "04", "avg": 114.05109489051095}, {"subreddit": "GoCommitDie", "hour": "05", "avg": 66.23728813559322}, {"subreddit": "GoCommitDie", "hour": "06", "avg": 142.5157894736842}, {"subreddit": "GoCommitDie", "hour": "07", "avg": 99.10975609756098}, {"subreddit": "GoCommitDie", "hour": "08", "avg": 51.06060606060606}, {"subreddit": "GoCommitDie", "hour": "09", "avg": 333.84057971014494}, {"subreddit": "GoCommitDie", "hour": "10", "avg": 118.91176470588235}, {"subreddit": "GoCommitDie", "hour": "11", "avg": 486.9113924050633}, {"subreddit": "GoCommitDie", "hour": "12", "avg": 324.05128205128204}, {"subreddit": "GoCommitDie", "hour": "13", "avg": 187.82857142857142}, {"subreddit": "GoCommitDie", "hour": "14", "avg": 331.91525423728814}, {"subreddit": "GoCommitDie", "hour": "15", "avg": 104.65517241379311}, {"subreddit": "GoCommitDie", "hour": "16", "avg": 202.67549668874173}, {"subreddit": "GoCommitDie", "hour": "17", "avg": 69.93922651933701}, {"subreddit": "GoCommitDie", "hour": "18", "avg": 90.84239130434783}, {"subreddit": "GoCommitDie", "hour": "19", "avg": 98.32768361581921}, {"subreddit": "GoCommitDie", "hour": "20", "avg": 104.5409090909091}, {"subreddit": "GoCommitDie", "hour": "21", "avg": 42.59090909090909}, {"subreddit": "GoCommitDie", "hour": "22", "avg": 94.7584541062802}, {"subreddit": "GoCommitDie", "hour": "23", "avg": 158.3764705882353}]