[{"subreddit": "GoneMildPlus", "hour": "01", "avg": 35.0625}, {"subreddit": "GoneMildPlus", "hour": "02", "avg": 40.839285714285715}, {"subreddit": "GoneMildPlus", "hour": "03", "avg": 36.10144927536232}, {"subreddit": "GoneMildPlus", "hour": "04", "avg": 36.16438356164384}, {"subreddit": "GoneMildPlus", "hour": "05", "avg": 35.90769230769231}, {"subreddit": "GoneMildPlus", "hour": "06", "avg": 28.120689655172413}, {"subreddit": "GoneMildPlus", "hour": "07", "avg": 30.424242424242426}, {"subreddit": "GoneMildPlus", "hour": "08", "avg": 32.45454545454545}, {"subreddit": "GoneMildPlus", "hour": "09", "avg": 50.357142857142854}, {"subreddit": "GoneMildPlus", "hour": "10", "avg": 30.17391304347826}, {"subreddit": "GoneMildPlus", "hour": "11", "avg": 58.9}, {"subreddit": "GoneMildPlus", "hour": "12", "avg": 21.470588235294116}, {"subreddit": "GoneMildPlus", "hour": "13", "avg": 56.148148148148145}, {"subreddit": "GoneMildPlus", "hour": "14", "avg": 72.11904761904762}, {"subreddit": "GoneMildPlus", "hour": "15", "avg": 77.33333333333333}, {"subreddit": "GoneMildPlus", "hour": "16", "avg": 46.89473684210526}, {"subreddit": "GoneMildPlus", "hour": "17", "avg": 39.97222222222222}, {"subreddit": "GoneMildPlus", "hour": "18", "avg": 36.10204081632653}, {"subreddit": "GoneMildPlus", "hour": "19", "avg": 52.91111111111111}, {"subreddit": "GoneMildPlus", "hour": "20", "avg": 40.73684210526316}, {"subreddit": "GoneMildPlus", "hour": "21", "avg": 56.53061224489796}, {"subreddit": "GoneMildPlus", "hour": "22", "avg": 36.41935483870968}, {"subreddit": "GoneMildPlus", "hour": "23", "avg": 44.083333333333336}]