[{"subreddit": "Gunners", "hour": "01", "avg": 83.5764705882353}, {"subreddit": "Gunners", "hour": "02", "avg": 131.88524590163934}, {"subreddit": "Gunners", "hour": "03", "avg": 105.53846153846153}, {"subreddit": "Gunners", "hour": "04", "avg": 81.21621621621621}, {"subreddit": "Gunners", "hour": "05", "avg": 119.01960784313725}, {"subreddit": "Gunners", "hour": "06", "avg": 57.630434782608695}, {"subreddit": "Gunners", "hour": "07", "avg": 130.7377049180328}, {"subreddit": "Gunners", "hour": "08", "avg": 78.72115384615384}, {"subreddit": "Gunners", "hour": "09", "avg": 64.4054054054054}, {"subreddit": "Gunners", "hour": "10", "avg": 47.5}, {"subreddit": "Gunners", "hour": "11", "avg": 113.6474358974359}, {"subreddit": "Gunners", "hour": "12", "avg": 113.7719298245614}, {"subreddit": "Gunners", "hour": "13", "avg": 86.61849710982659}, {"subreddit": "Gunners", "hour": "14", "avg": 117.33640552995392}, {"subreddit": "Gunners", "hour": "15", "avg": 78.20197044334975}, {"subreddit": "Gunners", "hour": "16", "avg": 95.12295081967213}, {"subreddit": "Gunners", "hour": "17", "avg": 100.07239819004525}, {"subreddit": "Gunners", "hour": "18", "avg": 106.15811965811966}, {"subreddit": "Gunners", "hour": "19", "avg": 92.64545454545454}, {"subreddit": "Gunners", "hour": "20", "avg": 97.109375}, {"subreddit": "Gunners", "hour": "21", "avg": 106.32342007434944}, {"subreddit": "Gunners", "hour": "22", "avg": 79.95027624309392}, {"subreddit": "Gunners", "hour": "23", "avg": 105.43181818181819}]