[{"subreddit": "iphonexwallpapers", "hour": "01", "avg": 17.27777777777778}, {"subreddit": "iphonexwallpapers", "hour": "02", "avg": 11.772727272727273}, {"subreddit": "iphonexwallpapers", "hour": "03", "avg": 15.5}, {"subreddit": "iphonexwallpapers", "hour": "04", "avg": 9.833333333333334}, {"subreddit": "iphonexwallpapers", "hour": "05", "avg": 4.6}, {"subreddit": "iphonexwallpapers", "hour": "06", "avg": 21.866666666666667}, {"subreddit": "iphonexwallpapers", "hour": "07", "avg": 6.333333333333333}, {"subreddit": "iphonexwallpapers", "hour": "08", "avg": 33.45454545454545}, {"subreddit": "iphonexwallpapers", "hour": "09", "avg": 2.6666666666666665}, {"subreddit": "iphonexwallpapers", "hour": "10", "avg": 17.285714285714285}, {"subreddit": "iphonexwallpapers", "hour": "11", "avg": 5.909090909090909}, {"subreddit": "iphonexwallpapers", "hour": "12", "avg": 24.454545454545453}, {"subreddit": "iphonexwallpapers", "hour": "13", "avg": 25.1875}, {"subreddit": "iphonexwallpapers", "hour": "14", "avg": 18.846153846153847}, {"subreddit": "iphonexwallpapers", "hour": "15", "avg": 12.3125}, {"subreddit": "iphonexwallpapers", "hour": "16", "avg": 24.057142857142857}, {"subreddit": "iphonexwallpapers", "hour": "17", "avg": 16.041666666666668}, {"subreddit": "iphonexwallpapers", "hour": "18", "avg": 13.96}, {"subreddit": "iphonexwallpapers", "hour": "19", "avg": 9.142857142857142}, {"subreddit": "iphonexwallpapers", "hour": "20", "avg": 18.333333333333332}, {"subreddit": "iphonexwallpapers", "hour": "21", "avg": 19.72222222222222}, {"subreddit": "iphonexwallpapers", "hour": "22", "avg": 10.380952380952381}, {"subreddit": "iphonexwallpapers", "hour": "23", "avg": 17.34375}]