[{"subreddit": "jhartifttt", "hour": "01", "avg": 1.0}, {"subreddit": "jhartifttt", "hour": "02", "avg": 1.0}, {"subreddit": "jhartifttt", "hour": "03", "avg": 1.0}, {"subreddit": "jhartifttt", "hour": "04", "avg": 1.0}, {"subreddit": "jhartifttt", "hour": "05", "avg": 1.1666666666666667}, {"subreddit": "jhartifttt", "hour": "06", "avg": 1.0}, {"subreddit": "jhartifttt", "hour": "07", "avg": 1.0}, {"subreddit": "jhartifttt", "hour": "08", "avg": 1.0714285714285714}, {"subreddit": "jhartifttt", "hour": "09", "avg": 1.0}, {"subreddit": "jhartifttt", "hour": "10", "avg": 0.9166666666666666}, {"subreddit": "jhartifttt", "hour": "11", "avg": 1.0}, {"subreddit": "jhartifttt", "hour": "12", "avg": 1.0}, {"subreddit": "jhartifttt", "hour": "13", "avg": 1.0909090909090908}, {"subreddit": "jhartifttt", "hour": "14", "avg": 1.0303030303030303}, {"subreddit": "jhartifttt", "hour": "15", "avg": 1.0192307692307692}, {"subreddit": "jhartifttt", "hour": "16", "avg": 1.0}, {"subreddit": "jhartifttt", "hour": "17", "avg": 1.0}, {"subreddit": "jhartifttt", "hour": "18", "avg": 1.0232558139534884}, {"subreddit": "jhartifttt", "hour": "19", "avg": 1.0307692307692307}, {"subreddit": "jhartifttt", "hour": "20", "avg": 1.0444444444444445}, {"subreddit": "jhartifttt", "hour": "21", "avg": 1.0416666666666667}, {"subreddit": "jhartifttt", "hour": "22", "avg": 1.09375}, {"subreddit": "jhartifttt", "hour": "23", "avg": 1.3333333333333333}]