[{"subreddit": "MakeNewFriendsHere", "hour": "01", "avg": 3.0725552050473186}, {"subreddit": "MakeNewFriendsHere", "hour": "02", "avg": 6.6875}, {"subreddit": "MakeNewFriendsHere", "hour": "03", "avg": 3.923636363636364}, {"subreddit": "MakeNewFriendsHere", "hour": "04", "avg": 3.3627118644067795}, {"subreddit": "MakeNewFriendsHere", "hour": "05", "avg": 4.988095238095238}, {"subreddit": "MakeNewFriendsHere", "hour": "06", "avg": 5.392712550607287}, {"subreddit": "MakeNewFriendsHere", "hour": "07", "avg": 3.853982300884956}, {"subreddit": "MakeNewFriendsHere", "hour": "08", "avg": 4.536945812807882}, {"subreddit": "MakeNewFriendsHere", "hour": "09", "avg": 5.1017964071856285}, {"subreddit": "MakeNewFriendsHere", "hour": "10", "avg": 4.527777777777778}, {"subreddit": "MakeNewFriendsHere", "hour": "11", "avg": 4.45679012345679}, {"subreddit": "MakeNewFriendsHere", "hour": "12", "avg": 7.169934640522876}, {"subreddit": "MakeNewFriendsHere", "hour": "13", "avg": 3.6}, {"subreddit": "MakeNewFriendsHere", "hour": "14", "avg": 3.7962962962962963}, {"subreddit": "MakeNewFriendsHere", "hour": "15", "avg": 6.795238095238095}, {"subreddit": "MakeNewFriendsHere", "hour": "16", "avg": 3.734126984126984}, {"subreddit": "MakeNewFriendsHere", "hour": "17", "avg": 5.9652509652509655}, {"subreddit": "MakeNewFriendsHere", "hour": "18", "avg": 5.270742358078603}, {"subreddit": "MakeNewFriendsHere", "hour": "19", "avg": 4.918367346938775}, {"subreddit": "MakeNewFriendsHere", "hour": "20", "avg": 7.117437722419929}, {"subreddit": "MakeNewFriendsHere", "hour": "21", "avg": 5.034364261168385}, {"subreddit": "MakeNewFriendsHere", "hour": "22", "avg": 6.582758620689655}, {"subreddit": "MakeNewFriendsHere", "hour": "23", "avg": 4.254658385093168}]