[{"subreddit": "MysteryDungeon", "hour": "01", "avg": 28.615384615384617}, {"subreddit": "MysteryDungeon", "hour": "02", "avg": 58.875}, {"subreddit": "MysteryDungeon", "hour": "03", "avg": 21.22222222222222}, {"subreddit": "MysteryDungeon", "hour": "04", "avg": 21.833333333333332}, {"subreddit": "MysteryDungeon", "hour": "05", "avg": 33.8}, {"subreddit": "MysteryDungeon", "hour": "06", "avg": 165.33333333333334}, {"subreddit": "MysteryDungeon", "hour": "07", "avg": 137.66666666666666}, {"subreddit": "MysteryDungeon", "hour": "08", "avg": 29.0}, {"subreddit": "MysteryDungeon", "hour": "09", "avg": 25.75}, {"subreddit": "MysteryDungeon", "hour": "10", "avg": 87.57142857142857}, {"subreddit": "MysteryDungeon", "hour": "11", "avg": 12.666666666666666}, {"subreddit": "MysteryDungeon", "hour": "12", "avg": 53.0}, {"subreddit": "MysteryDungeon", "hour": "13", "avg": 56.142857142857146}, {"subreddit": "MysteryDungeon", "hour": "14", "avg": 32.285714285714285}, {"subreddit": "MysteryDungeon", "hour": "15", "avg": 42.25}, {"subreddit": "MysteryDungeon", "hour": "16", "avg": 66.375}, {"subreddit": "MysteryDungeon", "hour": "17", "avg": 103.5}, {"subreddit": "MysteryDungeon", "hour": "18", "avg": 25.0}, {"subreddit": "MysteryDungeon", "hour": "19", "avg": 42.8}, {"subreddit": "MysteryDungeon", "hour": "20", "avg": 29.5}, {"subreddit": "MysteryDungeon", "hour": "21", "avg": 3.8}, {"subreddit": "MysteryDungeon", "hour": "22", "avg": 11.0}, {"subreddit": "MysteryDungeon", "hour": "23", "avg": 11.0}]