[{"subreddit": "phoenix", "hour": "01", "avg": 42.588235294117645}, {"subreddit": "phoenix", "hour": "02", "avg": 24.833333333333332}, {"subreddit": "phoenix", "hour": "03", "avg": 23.72093023255814}, {"subreddit": "phoenix", "hour": "04", "avg": 21.692307692307693}, {"subreddit": "phoenix", "hour": "05", "avg": 16.08823529411765}, {"subreddit": "phoenix", "hour": "06", "avg": 54.464285714285715}, {"subreddit": "phoenix", "hour": "07", "avg": 15.823529411764707}, {"subreddit": "phoenix", "hour": "08", "avg": 79.63636363636364}, {"subreddit": "phoenix", "hour": "09", "avg": 6.444444444444445}, {"subreddit": "phoenix", "hour": "10", "avg": 20.0}, {"subreddit": "phoenix", "hour": "11", "avg": 31.0}, {"subreddit": "phoenix", "hour": "12", "avg": 78.71428571428571}, {"subreddit": "phoenix", "hour": "13", "avg": 37.867924528301884}, {"subreddit": "phoenix", "hour": "14", "avg": 98.62962962962963}, {"subreddit": "phoenix", "hour": "15", "avg": 85.92727272727272}, {"subreddit": "phoenix", "hour": "16", "avg": 46.979166666666664}, {"subreddit": "phoenix", "hour": "17", "avg": 67.76923076923077}, {"subreddit": "phoenix", "hour": "18", "avg": 42.80769230769231}, {"subreddit": "phoenix", "hour": "19", "avg": 59.791666666666664}, {"subreddit": "phoenix", "hour": "20", "avg": 48.5}, {"subreddit": "phoenix", "hour": "21", "avg": 41.86274509803921}, {"subreddit": "phoenix", "hour": "22", "avg": 34.204081632653065}, {"subreddit": "phoenix", "hour": "23", "avg": 30.962264150943398}]