[{"subreddit": "PremierLeague", "hour": "01", "avg": 3.375}, {"subreddit": "PremierLeague", "hour": "02", "avg": 72.3125}, {"subreddit": "PremierLeague", "hour": "03", "avg": 11.714285714285714}, {"subreddit": "PremierLeague", "hour": "04", "avg": 1.3333333333333333}, {"subreddit": "PremierLeague", "hour": "05", "avg": 2.5}, {"subreddit": "PremierLeague", "hour": "06", "avg": 1.25}, {"subreddit": "PremierLeague", "hour": "07", "avg": 51.111111111111114}, {"subreddit": "PremierLeague", "hour": "08", "avg": 14.7}, {"subreddit": "PremierLeague", "hour": "09", "avg": 16.6875}, {"subreddit": "PremierLeague", "hour": "10", "avg": 1.9285714285714286}, {"subreddit": "PremierLeague", "hour": "11", "avg": 58.36363636363637}, {"subreddit": "PremierLeague", "hour": "12", "avg": 28.304347826086957}, {"subreddit": "PremierLeague", "hour": "13", "avg": 21.137931034482758}, {"subreddit": "PremierLeague", "hour": "14", "avg": 38.42857142857143}, {"subreddit": "PremierLeague", "hour": "15", "avg": 10.73076923076923}, {"subreddit": "PremierLeague", "hour": "16", "avg": 8.173913043478262}, {"subreddit": "PremierLeague", "hour": "17", "avg": 34.535714285714285}, {"subreddit": "PremierLeague", "hour": "18", "avg": 26.0}, {"subreddit": "PremierLeague", "hour": "19", "avg": 7.82051282051282}, {"subreddit": "PremierLeague", "hour": "20", "avg": 46.4}, {"subreddit": "PremierLeague", "hour": "21", "avg": 16.63157894736842}, {"subreddit": "PremierLeague", "hour": "22", "avg": 6.7407407407407405}, {"subreddit": "PremierLeague", "hour": "23", "avg": 1.7058823529411764}]