[{"subreddit": "PrequelMemes", "hour": "01", "avg": 229.25017869907077}, {"subreddit": "PrequelMemes", "hour": "02", "avg": 286.68333333333334}, {"subreddit": "PrequelMemes", "hour": "03", "avg": 239.92059336823735}, {"subreddit": "PrequelMemes", "hour": "04", "avg": 205.75500476644424}, {"subreddit": "PrequelMemes", "hour": "05", "avg": 290.3237486687966}, {"subreddit": "PrequelMemes", "hour": "06", "avg": 532.6390685640363}, {"subreddit": "PrequelMemes", "hour": "07", "avg": 461.23342541436466}, {"subreddit": "PrequelMemes", "hour": "08", "avg": 654.7203252032521}, {"subreddit": "PrequelMemes", "hour": "09", "avg": 567.7427101200686}, {"subreddit": "PrequelMemes", "hour": "10", "avg": 838.4579439252336}, {"subreddit": "PrequelMemes", "hour": "11", "avg": 756.6045673076923}, {"subreddit": "PrequelMemes", "hour": "12", "avg": 769.2178502879078}, {"subreddit": "PrequelMemes", "hour": "13", "avg": 524.7591508052709}, {"subreddit": "PrequelMemes", "hour": "14", "avg": 675.1011560693642}, {"subreddit": "PrequelMemes", "hour": "15", "avg": 323.27891156462584}, {"subreddit": "PrequelMemes", "hour": "16", "avg": 384.54058823529414}, {"subreddit": "PrequelMemes", "hour": "17", "avg": 300.83597883597884}, {"subreddit": "PrequelMemes", "hour": "18", "avg": 336.5684891240447}, {"subreddit": "PrequelMemes", "hour": "19", "avg": 364.62087264150944}, {"subreddit": "PrequelMemes", "hour": "20", "avg": 284.18046357615896}, {"subreddit": "PrequelMemes", "hour": "21", "avg": 276.8614492753623}, {"subreddit": "PrequelMemes", "hour": "22", "avg": 318.7852507374631}, {"subreddit": "PrequelMemes", "hour": "23", "avg": 224.75212002609263}]