[{"subreddit": "questions", "hour": "01", "avg": 2.480769230769231}, {"subreddit": "questions", "hour": "02", "avg": 2.595744680851064}, {"subreddit": "questions", "hour": "03", "avg": 2.404255319148936}, {"subreddit": "questions", "hour": "04", "avg": 2.888888888888889}, {"subreddit": "questions", "hour": "05", "avg": 2.358974358974359}, {"subreddit": "questions", "hour": "06", "avg": 2.742857142857143}, {"subreddit": "questions", "hour": "07", "avg": 1.6764705882352942}, {"subreddit": "questions", "hour": "08", "avg": 2.1666666666666665}, {"subreddit": "questions", "hour": "09", "avg": 2.5}, {"subreddit": "questions", "hour": "10", "avg": 1.8529411764705883}, {"subreddit": "questions", "hour": "11", "avg": 3.0714285714285716}, {"subreddit": "questions", "hour": "12", "avg": 1.4375}, {"subreddit": "questions", "hour": "13", "avg": 6.027027027027027}, {"subreddit": "questions", "hour": "14", "avg": 2.52}, {"subreddit": "questions", "hour": "15", "avg": 4.633333333333334}, {"subreddit": "questions", "hour": "16", "avg": 1.95}, {"subreddit": "questions", "hour": "17", "avg": 3.46875}, {"subreddit": "questions", "hour": "18", "avg": 3.3947368421052633}, {"subreddit": "questions", "hour": "19", "avg": 2.2325581395348837}, {"subreddit": "questions", "hour": "20", "avg": 2.619047619047619}, {"subreddit": "questions", "hour": "21", "avg": 1.5348837209302326}, {"subreddit": "questions", "hour": "22", "avg": 2.0217391304347827}, {"subreddit": "questions", "hour": "23", "avg": 2.625}]