[{"subreddit": "RDR2mysteries", "hour": "01", "avg": 16.5}, {"subreddit": "RDR2mysteries", "hour": "02", "avg": 8.571428571428571}, {"subreddit": "RDR2mysteries", "hour": "03", "avg": 10.181818181818182}, {"subreddit": "RDR2mysteries", "hour": "04", "avg": 20.428571428571427}, {"subreddit": "RDR2mysteries", "hour": "05", "avg": 9.2}, {"subreddit": "RDR2mysteries", "hour": "06", "avg": 12.083333333333334}, {"subreddit": "RDR2mysteries", "hour": "07", "avg": 13.0}, {"subreddit": "RDR2mysteries", "hour": "08", "avg": 15.666666666666666}, {"subreddit": "RDR2mysteries", "hour": "09", "avg": 12.5}, {"subreddit": "RDR2mysteries", "hour": "10", "avg": 13.0}, {"subreddit": "RDR2mysteries", "hour": "11", "avg": 9.833333333333334}, {"subreddit": "RDR2mysteries", "hour": "12", "avg": 14.0}, {"subreddit": "RDR2mysteries", "hour": "13", "avg": 11.428571428571429}, {"subreddit": "RDR2mysteries", "hour": "14", "avg": 5.0}, {"subreddit": "RDR2mysteries", "hour": "15", "avg": 13.0}, {"subreddit": "RDR2mysteries", "hour": "16", "avg": 6.833333333333333}, {"subreddit": "RDR2mysteries", "hour": "17", "avg": 16.0}, {"subreddit": "RDR2mysteries", "hour": "18", "avg": 5.857142857142857}, {"subreddit": "RDR2mysteries", "hour": "19", "avg": 10.166666666666666}, {"subreddit": "RDR2mysteries", "hour": "20", "avg": 22.25}, {"subreddit": "RDR2mysteries", "hour": "21", "avg": 11.473684210526315}, {"subreddit": "RDR2mysteries", "hour": "22", "avg": 11.777777777777779}, {"subreddit": "RDR2mysteries", "hour": "23", "avg": 12.4375}]