[{"subreddit": "slavelabour", "hour": "01", "avg": 6.059907834101383}, {"subreddit": "slavelabour", "hour": "02", "avg": 3.4654088050314464}, {"subreddit": "slavelabour", "hour": "03", "avg": 3.015151515151515}, {"subreddit": "slavelabour", "hour": "04", "avg": 2.9647058823529413}, {"subreddit": "slavelabour", "hour": "05", "avg": 1.4906832298136645}, {"subreddit": "slavelabour", "hour": "06", "avg": 2.2158273381294964}, {"subreddit": "slavelabour", "hour": "07", "avg": 1.4339622641509433}, {"subreddit": "slavelabour", "hour": "08", "avg": 2.121212121212121}, {"subreddit": "slavelabour", "hour": "09", "avg": 3.1132075471698113}, {"subreddit": "slavelabour", "hour": "10", "avg": 7.336956521739131}, {"subreddit": "slavelabour", "hour": "11", "avg": 5.05607476635514}, {"subreddit": "slavelabour", "hour": "12", "avg": 1.9827586206896552}, {"subreddit": "slavelabour", "hour": "13", "avg": 3.7109375}, {"subreddit": "slavelabour", "hour": "14", "avg": 4.401234567901234}, {"subreddit": "slavelabour", "hour": "15", "avg": 5.188405797101449}, {"subreddit": "slavelabour", "hour": "16", "avg": 4.551020408163265}, {"subreddit": "slavelabour", "hour": "17", "avg": 3.014218009478673}, {"subreddit": "slavelabour", "hour": "18", "avg": 2.8347826086956522}, {"subreddit": "slavelabour", "hour": "19", "avg": 2.6406926406926408}, {"subreddit": "slavelabour", "hour": "20", "avg": 7.504385964912281}, {"subreddit": "slavelabour", "hour": "21", "avg": 2.818548387096774}, {"subreddit": "slavelabour", "hour": "22", "avg": 3.1330645161290325}, {"subreddit": "slavelabour", "hour": "23", "avg": 3.1448598130841123}]