[{"subreddit": "thanosdidnothingwrong", "hour": "01", "avg": 302.8072289156627}, {"subreddit": "thanosdidnothingwrong", "hour": "02", "avg": 343.0118343195266}, {"subreddit": "thanosdidnothingwrong", "hour": "03", "avg": 116.06666666666666}, {"subreddit": "thanosdidnothingwrong", "hour": "04", "avg": 131.94871794871796}, {"subreddit": "thanosdidnothingwrong", "hour": "05", "avg": 28.357954545454547}, {"subreddit": "thanosdidnothingwrong", "hour": "06", "avg": 35.2969696969697}, {"subreddit": "thanosdidnothingwrong", "hour": "07", "avg": 642.650406504065}, {"subreddit": "thanosdidnothingwrong", "hour": "08", "avg": 393.4018691588785}, {"subreddit": "thanosdidnothingwrong", "hour": "09", "avg": 26.46875}, {"subreddit": "thanosdidnothingwrong", "hour": "10", "avg": 173.23157894736843}, {"subreddit": "thanosdidnothingwrong", "hour": "11", "avg": 1818.5421686746988}, {"subreddit": "thanosdidnothingwrong", "hour": "12", "avg": 1118.4503816793892}, {"subreddit": "thanosdidnothingwrong", "hour": "13", "avg": 738.9290780141844}, {"subreddit": "thanosdidnothingwrong", "hour": "14", "avg": 847.6395348837209}, {"subreddit": "thanosdidnothingwrong", "hour": "15", "avg": 848.5373134328358}, {"subreddit": "thanosdidnothingwrong", "hour": "16", "avg": 194.55042016806723}, {"subreddit": "thanosdidnothingwrong", "hour": "17", "avg": 620.6359223300971}, {"subreddit": "thanosdidnothingwrong", "hour": "18", "avg": 297.68918918918916}, {"subreddit": "thanosdidnothingwrong", "hour": "19", "avg": 159.19138755980862}, {"subreddit": "thanosdidnothingwrong", "hour": "20", "avg": 202.45581395348836}, {"subreddit": "thanosdidnothingwrong", "hour": "21", "avg": 258.3457943925234}, {"subreddit": "thanosdidnothingwrong", "hour": "22", "avg": 418.02777777777777}, {"subreddit": "thanosdidnothingwrong", "hour": "23", "avg": 292.8412698412698}]