[{"subreddit": "uscg", "hour": "01", "avg": 18.36}, {"subreddit": "uscg", "hour": "02", "avg": 27.434782608695652}, {"subreddit": "uscg", "hour": "03", "avg": 11.733333333333333}, {"subreddit": "uscg", "hour": "04", "avg": 22.789473684210527}, {"subreddit": "uscg", "hour": "05", "avg": 12.8}, {"subreddit": "uscg", "hour": "06", "avg": 30.4}, {"subreddit": "uscg", "hour": "07", "avg": 4.0}, {"subreddit": "uscg", "hour": "08", "avg": 1.5}, {"subreddit": "uscg", "hour": "09", "avg": 2.0}, {"subreddit": "uscg", "hour": "10", "avg": 14.75}, {"subreddit": "uscg", "hour": "11", "avg": 68.6}, {"subreddit": "uscg", "hour": "12", "avg": 21.5}, {"subreddit": "uscg", "hour": "13", "avg": 31.083333333333332}, {"subreddit": "uscg", "hour": "14", "avg": 6.5}, {"subreddit": "uscg", "hour": "15", "avg": 15.5}, {"subreddit": "uscg", "hour": "16", "avg": 14.23076923076923}, {"subreddit": "uscg", "hour": "17", "avg": 16.153846153846153}, {"subreddit": "uscg", "hour": "18", "avg": 52.875}, {"subreddit": "uscg", "hour": "19", "avg": 39.96875}, {"subreddit": "uscg", "hour": "20", "avg": 20.333333333333332}, {"subreddit": "uscg", "hour": "21", "avg": 29.25}, {"subreddit": "uscg", "hour": "22", "avg": 9.846153846153847}, {"subreddit": "uscg", "hour": "23", "avg": 24.52173913043478}]