{"day":"01","subreddit":"PewdiepieSubmissions","posts":168}
{"day":"01","subreddit":"PhDCafe","posts":1}
{"day":"01","subreddit":"PhantomForces","posts":1}
{"day":"01","subreddit":"Philippines","posts":3}
{"day":"01","subreddit":"PhilosophyTube","posts":1}
{"day":"01","subreddit":"PhoenixLeagueLoL","posts":1}
{"day":"01","subreddit":"PhotoshopRequest","posts":1}
{"day":"01","subreddit":"Physics","posts":1}
{"day":"01","subreddit":"PickOne","posts":2}
{"day":"01","subreddit":"PicturesOfGreenThings","posts":1}
{"day":"01","subreddit":"Pins","posts":1}
{"day":"01","subreddit":"Pins4Skins","posts":1}
{"day":"01","subreddit":"Piracy","posts":1}
{"day":"01","subreddit":"Pixel3","posts":1}
{"day":"01","subreddit":"PixelArt","posts":3}
{"day":"01","subreddit":"PixelBook","posts":1}
{"day":"01","subreddit":"PixelCarRacer","posts":1}
{"day":"01","subreddit":"Pizza","posts":2}
